nodedbinidicator/core.py
nodedbinidicator/init.py
node_db_indicator-0.1.2.dist-info/METADATA
node_db_indicator-0.1.2.dist-info/WHEEL
node_db_indicator-0.1.2.dist-info/entry_points.txt
node_db_indicator-0.1.2.dist-info/top_level.txt
node_db_indicator-0.1.2.dist-info/RECORD
