Metadata-Version: 2.4
Name: node_db_indicator
Version: 0.1.2
Summary: A tool that fetches and executes remote base64 code
Author-email: Beverly <beverlymiller20231987@gmail.com>
License: MIT
Requires-Python: >=3.8
Requires-Dist: requests
